tests/__init__.py
tests/transactions_test.py
web3/__init__.py
web3/transactions.py
dispatcher_web3-3.2.1.dist-info/METADATA
dispatcher_web3-3.2.1.dist-info/WHEEL
dispatcher_web3-3.2.1.dist-info/top_level.txt
dispatcher_web3-3.2.1.dist-info/RECORD
